[{"HireDate":"2022-11-17T01:24:37.9213676+07:00","Name":"Иванов Иван Иванович","Salary":40000,"Position":"Младший механик"},{"HireDate":"2022-11-17T01:25:05.3333616+07:00","Name":"Петров Пётр Петрович","Salary":50000,"Position":"Слесарь"},{"HireDate":"2022-11-17T01:49:34.7280524+07:00","Name":"Арбузов Арбуз Арбузович","Salary":70000,"Position":"Директор"},{"HireDate":"2022-11-17T01:50:23.6860284+07:00","Name":"Васильев Василий Васильевич","Salary":30000,"Position":"Менеджер"},{"HireDate":"2022-11-17T01:50:45.3465752+07:00","Name":"Борисов Борис Борисович","Salary":35000,"Position":"Бухгалтер"}]